README.rst
setup.py
kian/__init__.py
kian/core.py
kian/fitness.py
kian/merge_parser_temp.py
kian/model.py
kian/parser.py
kian/trained_model.py
kian.egg-info/PKG-INFO
kian.egg-info/SOURCES.txt
kian.egg-info/dependency_links.txt
kian.egg-info/requires.txt
kian.egg-info/top_level.txt
scripts/__init__.py
scripts/clean_duplicates.py
scripts/evaluate.py
scripts/general.py
scripts/human_review_add.py
scripts/initiate_model.py
scripts/parse_and_add.py
scripts/parser.py
scripts/populate_database.py
scripts/populate_mistakes_database.py
scripts/possible_adds.py
scripts/possible_adds_svm.py
scripts/possible_mistakes.py
scripts/train_model.py