Metadata-Version: 1.1
Name: kian
Version: 0.2.0
Summary: Kian is the neural network designed to serve Wikidata.
Home-page: https://github.com/Ladsgroup/Kian
Author: Amir Sarabadani
Author-email: ladsgroup@gmail.com
License: MIT License
Platform: UNKNOWN
Classifier: License :: OSI Approved :: MIT License
Classifier: Development Status :: 3 - Alpha
Classifier: Operating System :: OS Independent
Classifier: Intended Audience :: Developers
Classifier: Environment :: Console
Classifier: Programming Language :: Python :: 2.7
Classifier: Programming Language :: Python :: 3.3
